commitcleaner/__init__.py
commitcleaner/cleaner.py
commitcleaner-0.6.0.dist-info/LICENSE
commitcleaner-0.6.0.dist-info/METADATA
commitcleaner-0.6.0.dist-info/WHEEL
commitcleaner-0.6.0.dist-info/entry_points.txt
commitcleaner-0.6.0.dist-info/top_level.txt
commitcleaner-0.6.0.dist-info/RECORD
